<annotation><foler>VOC2007</foler><filename>IMG_7017.JPG</filename><source><database>The VOC2007 Database</database><annotation>PASCAL VOC2007</annotation><image>RFV</image></source><size><width>900</width><height>1232</height><depth>3</depth></size><segmented>0</segmented><object><name>bullet</name><pose>Left</pose><truncated>1</truncated><difficult>0</difficult><bndbox><xmin>489</xmin><ymin>681</ymin><xmax>532</xmax><ymax>718</ymax></bndbox></object><object><name>bullet</name><pose>Left</pose><truncated>1</truncated><difficult>0</difficult><bndbox><xmin>412</xmin><ymin>624</ymin><xmax>450</xmax><ymax>660</ymax></bndbox></object></annotation>