<annotation><foler>VOC2007</foler><filename>IMG_7259.JPG</filename><source><database>The VOC2007 Database</database><annotation>PASCAL VOC2007</annotation><image>RFV</image></source><size><width>900</width><height>1304</height><depth>3</depth></size><segmented>0</segmented><object><name>bullet</name><pose>Left</pose><truncated>1</truncated><difficult>0</difficult><bndbox><xmin>510</xmin><ymin>384</ymin><xmax>535</xmax><ymax>410</ymax></bndbox></object><object><name>bullet</name><pose>Left</pose><truncated>1</truncated><difficult>0</difficult><bndbox><xmin>535</xmin><ymin>374</ymin><xmax>558</xmax><ymax>402</ymax></bndbox></object><object><name>bullet</name><pose>Left</pose><truncated>1</truncated><difficult>0</difficult><bndbox><xmin>486</xmin><ymin>497</ymin><xmax>525</xmax><ymax>532</ymax></bndbox></object><object><name>bullet</name><pose>Left</pose><truncated>1</truncated><difficult>0</difficult><bndbox><xmin>319</xmin><ymin>514</ymin><xmax>353</xmax><ymax>548</ymax></bndbox></object><object><name>bullet</name><pose>Left</pose><truncated>1</truncated><difficult>0</difficult><bndbox><xmin>376</xmin><ymin>823</ymin><xmax>407</xmax><ymax>856</ymax></bndbox></object></annotation>